digital_hydrant/__init__.py
digital_hydrant/__version__.py
digital_hydrant/args.py
digital_hydrant/collector_queue.py
digital_hydrant/commands.py
digital_hydrant/config.py
digital_hydrant/logging.py
digital_hydrant/main.py
digital_hydrant/migration.py
digital_hydrant/ping.py
digital_hydrant/process_manager.py
digital_hydrant/uploader.py
digital_hydrant/collectors/__init__.py
digital_hydrant/collectors/collector.py
digital_hydrant/collectors/dhcp/__init__.py
digital_hydrant/collectors/hydra/__init__.py
digital_hydrant/collectors/lldp/__init__.py
digital_hydrant/collectors/netdiscover/__init__.py
digital_hydrant/collectors/nmap/__init__.py
digital_hydrant/collectors/speedtest/__init__.py
digital_hydrant/collectors/vlan/__init__.py
digital_hydrant/collectors/wifi_auth/__init__.py
digital_hydrant/collectors/wifi_quality/__init__.py
digital_hydrant/collectors/wifi_quality/scan.py
digital_hydrant/config/config.ini
digital_hydrant/config/hydra/common-passwords.txt
digital_hydrant/config/hydra/snmp_wordlist.txt
digital_hydrant/config/hydra/userlist.txt
digital_hydrant/migrations/0001_base_tables.sql
digital_hydrant/migrations/0002_add_mac_to_ip_table.sql
digital_hydrant/migrations/0003_add_upload_error_to_collectors.sql
digital_hydrant/systemd/digital-hydrant.service
digital_hydrant-0.1.7.data/scripts/hydrant
test/__init__.py
test/test_collector_queue.py
test/test_config.py
test/test_process_manager.py
test/test_uploader.py
test/collectors/__init__.py
test/collectors/test_dhcp.py
test/collectors/test_hydra.py
test/collectors/test_lldp.py
test/collectors/test_netdiscover.py
test/collectors/test_nmap.py
test/collectors/test_speedtest.py
test/collectors/test_vlan.py
test/collectors/test_wifi_auth.py
test/collectors/test_wifi_quality.py
test/stub_collectors/__init__.py
test/stub_collectors/dhcp/__init__.py
test/stub_collectors/hydra/__init__.py
digital_hydrant-0.1.7.dist-info/LICENSE
digital_hydrant-0.1.7.dist-info/METADATA
digital_hydrant-0.1.7.dist-info/WHEEL
digital_hydrant-0.1.7.dist-info/top_level.txt
digital_hydrant-0.1.7.dist-info/RECORD
