Metadata-Version: 2.1
Name: digital-hydrant
Version: 0.1.7
Summary: Digital Hydrant Collectors
Home-page: https://github.com/outsideopen/digital-hydrant-collectors
Author: Outside Open
Author-email: developers@outsideopen.com
License: GPL
Platform: linux
License-File: LICENSE
Requires-Dist: colorlog
Requires-Dist: netifaces
Requires-Dist: py-singleton
Requires-Dist: requests
Requires-Dist: speedtest-cli
Requires-Dist: schedule
Requires-Dist: configupdater
Requires-Dist: python-nmap
